{"cameraMode":{"drawMode":0,"name":"Shaded","section":"Shading Mode"},"sceneLighting":true,"audioPlay":false,"sceneViewState":{"m_AlwaysRefresh":false,"showFog":true,"showSkybox":true,"showFlares":true,"showImageEffects":true,"showParticleSystems":true,"showVisualEffectGraphs":true,"m_FxEnabled":true},"in2DMode":false,"pivot":{"x":-2.3482561111450197,"y":-0.3509788513183594,"z":-5.801257133483887},"rotation":{"x":-0.06359872221946717,"y":0.9356063604354858,"z":-0.22480712831020356,"w":-0.26468637585639956},"size":10.0,"orthographic":false}